MANIFEST.in
RELEASE-VERSION
pavement.py
paver-minilib.zip
setup.py
version.py
redirect_io/__init__.py
redirect_io.egg-info/PKG-INFO
redirect_io.egg-info/SOURCES.txt
redirect_io.egg-info/dependency_links.txt
redirect_io.egg-info/top_level.txt