Metadata-Version: 1.0
Name: redirect-io
Version: 0.1
Summary: Context managers to redirect stderr or stdout.
Home-page: https://github.com/wheeler-microfluidics/redirect-io
Author: Christian Fobel
Author-email: christian@fobel.net
License: GPL
Keywords: stdout,stderr,context manager
Platform: UNKNOWN
